resvg_python-0.1.0.dist-info/METADATA
resvg_python-0.1.0.dist-info/WHEEL
resvg_python/__init__.py
resvg_python/resvg_python.pypy310-pp73-x86-linux-gnu.so
resvg_python-0.1.0.dist-info/RECORD
