Metadata-Version: 2.3
Name: resvg_python
Version: 0.1.0
